lilypond.py
lilypond-binaries/bin/abc2ly.py
lilypond-binaries/bin/convert-ly.py
lilypond-binaries/bin/etf2ly.py
lilypond-binaries/bin/gspawn-win64-helper-console.exe
lilypond-binaries/bin/libgio-2.0-0.dll
lilypond-binaries/bin/libglib-2.0-0.dll
lilypond-binaries/bin/libgmodule-2.0-0.dll
lilypond-binaries/bin/libgobject-2.0-0.dll
lilypond-binaries/bin/libintl-8.dll
lilypond-binaries/bin/lilymidi.py
lilypond-binaries/bin/lilypond-book.py
lilypond-binaries/bin/lilypond-invoke-editor.py
lilypond-binaries/bin/lilypond.exe
lilypond-binaries/bin/midi2ly.py
lilypond-binaries/bin/musicxml2ly.py
lilypond-binaries/bin/pyexpat.pyd
lilypond-binaries/bin/python.exe
lilypond-binaries/bin/python310.dll
lilypond-binaries/bin/python310.zip
lilypond-binaries/etc/fonts/fonts.conf
lilypond-binaries/etc/fonts/conf.d/10-hinting-slight.conf
lilypond-binaries/etc/fonts/conf.d/10-scale-bitmap-fonts.conf
lilypond-binaries/etc/fonts/conf.d/10-sub-pixel-none.conf
lilypond-binaries/etc/fonts/conf.d/10-yes-antialias.conf
lilypond-binaries/etc/fonts/conf.d/11-lcdfilter-default.conf
lilypond-binaries/etc/fonts/conf.d/20-unhint-small-vera.conf
lilypond-binaries/etc/fonts/conf.d/30-metric-aliases.conf
lilypond-binaries/etc/fonts/conf.d/40-nonlatin.conf
lilypond-binaries/etc/fonts/conf.d/45-generic.conf
lilypond-binaries/etc/fonts/conf.d/45-latin.conf
lilypond-binaries/etc/fonts/conf.d/48-spacing.conf
lilypond-binaries/etc/fonts/conf.d/49-sansserif.conf
lilypond-binaries/etc/fonts/conf.d/50-user.conf
lilypond-binaries/etc/fonts/conf.d/51-local.conf
lilypond-binaries/etc/fonts/conf.d/60-generic.conf
lilypond-binaries/etc/fonts/conf.d/60-latin.conf
lilypond-binaries/etc/fonts/conf.d/65-fonts-persian.conf
lilypond-binaries/etc/fonts/conf.d/65-nonlatin.conf
lilypond-binaries/etc/fonts/conf.d/69-unifont.conf
lilypond-binaries/etc/fonts/conf.d/80-delicious.conf
lilypond-binaries/etc/fonts/conf.d/90-synthetic.conf
lilypond-binaries/etc/fonts/conf.d/README
lilypond-2.25.12.dist-info/METADATA
lilypond-2.25.12.dist-info/WHEEL
