Metadata-Version: 2.1
Name: lilypond
Version: 2.25.12
Home-page: https://gitlab.com/jeanas/lilypond-wheels.git
License: GPL-3.0-or-later
Summary: A redistribution of LilyPond to use it easily from Python code.
